odoo9_addon_openeducat_facility-9.0.2.4.0-py2.7-nspkg.pth
odoo_addons/openeducat_facility/__openerp__.py
odoo_addons/openeducat_facility/__init__.py
odoo_addons/openeducat_facility/facility_menu.xml
odoo_addons/openeducat_facility/security/ir.model.access.csv
odoo_addons/openeducat_facility/models/facility.py
odoo_addons/openeducat_facility/models/__init__.py
odoo_addons/openeducat_facility/models/facility_line.py
odoo_addons/openeducat_facility/i18n/openeducat_facility.pot
odoo_addons/openeducat_facility/views/facility_line_view.xml
odoo_addons/openeducat_facility/views/facility_view.xml
odoo_addons/openeducat_facility/demo/op.facility.csv
odoo_addons/openeducat_facility/static/description/openeducat_logo.png
odoo_addons/openeducat_facility/static/description/index.html
odoo_addons/openeducat_facility/static/description/facility.png
odoo_addons/openeducat_facility/static/description/openeducat_facility_banner.jpg
odoo_addons/openeducat_facility/static/description/icon.png
odoo9_addon_openeducat_facility-9.0.2.4.0.dist-info/top_level.txt
odoo9_addon_openeducat_facility-9.0.2.4.0.dist-info/WHEEL
odoo9_addon_openeducat_facility-9.0.2.4.0.dist-info/RECORD
odoo9_addon_openeducat_facility-9.0.2.4.0.dist-info/metadata.json
odoo9_addon_openeducat_facility-9.0.2.4.0.dist-info/DESCRIPTION.rst
odoo9_addon_openeducat_facility-9.0.2.4.0.dist-info/METADATA
odoo9_addon_openeducat_facility-9.0.2.4.0.dist-info/namespace_packages.txt
